dice/calculator.py
mycalc/calculator.py
cheondiccegamme1-0.0.2.dist-info/LICENSE
cheondiccegamme1-0.0.2.dist-info/METADATA
cheondiccegamme1-0.0.2.dist-info/WHEEL
cheondiccegamme1-0.0.2.dist-info/top_level.txt
cheondiccegamme1-0.0.2.dist-info/RECORD
